<?xml version='1.0' encoding='utf-8'?>
<Entries>
  <Entry>
    <PointerOffsetDec>742</PointerOffsetDec>
    <PointerOffsetHex>0x2e6</PointerOffsetHex>
    <JapaneseText>通常。</JapaneseText>
    <EnglishText />
    <Notes />
    <Id>50</Id>
    <Status />
  </Entry>
  <Entry>
    <PointerOffsetDec>751</PointerOffsetDec>
    <PointerOffsetHex>0x2ef</PointerOffsetHex>
    <JapaneseText>あめんぼ赤いなアイウエオ</JapaneseText>
    <EnglishText />
    <Notes />
    <Id>51</Id>
    <Status />
  </Entry>
  <Entry>
    <PointerOffsetDec>777</PointerOffsetDec>
    <PointerOffsetHex>0x309</PointerOffsetHex>
    <JapaneseText>柿木栗の木カキクケコ</JapaneseText>
    <EnglishText />
    <Notes />
    <Id>52</Id>
    <Status />
  </Entry>
  <Entry>
    <PointerOffsetDec>799</PointerOffsetDec>
    <PointerOffsetHex>0x31f</PointerOffsetHex>
    <JapaneseText>大角豆に酢をかけサシスセソ</JapaneseText>
    <EnglishText />
    <Notes />
    <Id>53</Id>
    <Status />
  </Entry>
  <Entry>
    <PointerOffsetDec>827</PointerOffsetDec>
    <PointerOffsetHex>0x33b</PointerOffsetHex>
    <JapaneseText>笑い。</JapaneseText>
    <EnglishText />
    <Notes />
    <Id>54</Id>
    <Status />
  </Entry>
  <Entry>
    <PointerOffsetDec>836</PointerOffsetDec>
    <PointerOffsetHex>0x344</PointerOffsetHex>
    <JapaneseText>あめんぼ赤いなアイウエオ</JapaneseText>
    <EnglishText />
    <Notes />
    <Id>55</Id>
    <Status />
  </Entry>
  <Entry>
    <PointerOffsetDec>862</PointerOffsetDec>
    <PointerOffsetHex>0x35e</PointerOffsetHex>
    <JapaneseText>柿木栗の木カキクケコ</JapaneseText>
    <EnglishText />
    <Notes />
    <Id>56</Id>
    <Status />
  </Entry>
  <Entry>
    <PointerOffsetDec>884</PointerOffsetDec>
    <PointerOffsetHex>0x374</PointerOffsetHex>
    <JapaneseText>大角豆に酢をかけサシスセソ</JapaneseText>
    <EnglishText />
    <Notes />
    <Id>57</Id>
    <Status />
  </Entry>
  <Entry>
    <PointerOffsetDec>912</PointerOffsetDec>
    <PointerOffsetHex>0x390</PointerOffsetHex>
    <JapaneseText>怒り。</JapaneseText>
    <EnglishText />
    <Notes />
    <Id>58</Id>
    <Status />
  </Entry>
  <Entry>
    <PointerOffsetDec>921</PointerOffsetDec>
    <PointerOffsetHex>0x399</PointerOffsetHex>
    <JapaneseText>あめんぼ赤いなアイウエオ</JapaneseText>
    <EnglishText />
    <Notes />
    <Id>59</Id>
    <Status />
  </Entry>
  <Entry>
    <PointerOffsetDec>947</PointerOffsetDec>
    <PointerOffsetHex>0x3b3</PointerOffsetHex>
    <JapaneseText>柿木栗の木カキクケコ</JapaneseText>
    <EnglishText />
    <Notes />
    <Id>60</Id>
    <Status />
  </Entry>
  <Entry>
    <PointerOffsetDec>969</PointerOffsetDec>
    <PointerOffsetHex>0x3c9</PointerOffsetHex>
    <JapaneseText>大角豆に酢をかけサシスセソ</JapaneseText>
    <EnglishText />
    <Notes />
    <Id>61</Id>
    <Status />
  </Entry>
  <Entry>
    <PointerOffsetDec>997</PointerOffsetDec>
    <PointerOffsetHex>0x3e5</PointerOffsetHex>
    <JapaneseText>ウンチク。</JapaneseText>
    <EnglishText />
    <Notes />
    <Id>62</Id>
    <Status />
  </Entry>
  <Entry>
    <PointerOffsetDec>1010</PointerOffsetDec>
    <PointerOffsetHex>0x3f2</PointerOffsetHex>
    <JapaneseText>あめんぼ赤いなアイウエオ</JapaneseText>
    <EnglishText />
    <Notes />
    <Id>63</Id>
    <Status />
  </Entry>
  <Entry>
    <PointerOffsetDec>1036</PointerOffsetDec>
    <PointerOffsetHex>0x40c</PointerOffsetHex>
    <JapaneseText>柿木栗の木カキクケコ</JapaneseText>
    <EnglishText />
    <Notes />
    <Id>64</Id>
    <Status />
  </Entry>
  <Entry>
    <PointerOffsetDec>1058</PointerOffsetDec>
    <PointerOffsetHex>0x422</PointerOffsetHex>
    <JapaneseText>大角豆に酢をかけサシスセソ</JapaneseText>
    <EnglishText />
    <Notes />
    <Id>65</Id>
    <Status />
  </Entry>
  <Entry>
    <PointerOffsetDec>1086</PointerOffsetDec>
    <PointerOffsetHex>0x43e</PointerOffsetHex>
    <JapaneseText>超喜び。</JapaneseText>
    <EnglishText />
    <Notes />
    <Id>66</Id>
    <Status />
  </Entry>
  <Entry>
    <PointerOffsetDec>1097</PointerOffsetDec>
    <PointerOffsetHex>0x449</PointerOffsetHex>
    <JapaneseText>あめんぼ赤いなアイウエオ</JapaneseText>
    <EnglishText />
    <Notes />
    <Id>67</Id>
    <Status />
  </Entry>
  <Entry>
    <PointerOffsetDec>1123</PointerOffsetDec>
    <PointerOffsetHex>0x463</PointerOffsetHex>
    <JapaneseText>柿木栗の木カキクケコ</JapaneseText>
    <EnglishText />
    <Notes />
    <Id>68</Id>
    <Status />
  </Entry>
  <Entry>
    <PointerOffsetDec>1145</PointerOffsetDec>
    <PointerOffsetHex>0x479</PointerOffsetHex>
    <JapaneseText>大角豆に酢をかけサシスセソ</JapaneseText>
    <EnglishText />
    <Notes />
    <Id>69</Id>
    <Status />
  </Entry>
  <Entry>
    <PointerOffsetDec>1173</PointerOffsetDec>
    <PointerOffsetHex>0x495</PointerOffsetHex>
    <JapaneseText>通常。</JapaneseText>
    <EnglishText />
    <Notes />
    <Id>70</Id>
    <Status />
  </Entry>
  <Entry>
    <PointerOffsetDec>1182</PointerOffsetDec>
    <PointerOffsetHex>0x49e</PointerOffsetHex>
    <JapaneseText>あめんぼ赤いなアイウエオ</JapaneseText>
    <EnglishText />
    <Notes />
    <Id>71</Id>
    <Status />
  </Entry>
  <Entry>
    <PointerOffsetDec>1208</PointerOffsetDec>
    <PointerOffsetHex>0x4b8</PointerOffsetHex>
    <JapaneseText>柿木栗の木カキクケコ</JapaneseText>
    <EnglishText />
    <Notes />
    <Id>72</Id>
    <Status />
  </Entry>
  <Entry>
    <PointerOffsetDec>1230</PointerOffsetDec>
    <PointerOffsetHex>0x4ce</PointerOffsetHex>
    <JapaneseText>大角豆に酢をかけサシスセソ</JapaneseText>
    <EnglishText />
    <Notes />
    <Id>73</Id>
    <Status />
  </Entry>
  <Entry>
    <PointerOffsetDec>1258</PointerOffsetDec>
    <PointerOffsetHex>0x4ea</PointerOffsetHex>
    <JapaneseText>笑い。</JapaneseText>
    <EnglishText />
    <Notes />
    <Id>74</Id>
    <Status />
  </Entry>
  <Entry>
    <PointerOffsetDec>1267</PointerOffsetDec>
    <PointerOffsetHex>0x4f3</PointerOffsetHex>
    <JapaneseText>あめんぼ赤いなアイウエオ</JapaneseText>
    <EnglishText />
    <Notes />
    <Id>75</Id>
    <Status />
  </Entry>
  <Entry>
    <PointerOffsetDec>1293</PointerOffsetDec>
    <PointerOffsetHex>0x50d</PointerOffsetHex>
    <JapaneseText>柿木栗の木カキクケコ</JapaneseText>
    <EnglishText />
    <Notes />
    <Id>76</Id>
    <Status />
  </Entry>
  <Entry>
    <PointerOffsetDec>1315</PointerOffsetDec>
    <PointerOffsetHex>0x523</PointerOffsetHex>
    <JapaneseText>大角豆に酢をかけサシスセソ</JapaneseText>
    <EnglishText />
    <Notes />
    <Id>77</Id>
    <Status />
  </Entry>
  <Entry>
    <PointerOffsetDec>1343</PointerOffsetDec>
    <PointerOffsetHex>0x53f</PointerOffsetHex>
    <JapaneseText>怒り。</JapaneseText>
    <EnglishText />
    <Notes />
    <Id>78</Id>
    <Status />
  </Entry>
  <Entry>
    <PointerOffsetDec>1352</PointerOffsetDec>
    <PointerOffsetHex>0x548</PointerOffsetHex>
    <JapaneseText>あめんぼ赤いなアイウエオ</JapaneseText>
    <EnglishText />
    <Notes />
    <Id>79</Id>
    <Status />
  </Entry>
  <Entry>
    <PointerOffsetDec>1378</PointerOffsetDec>
    <PointerOffsetHex>0x562</PointerOffsetHex>
    <JapaneseText>柿木栗の木カキクケコ</JapaneseText>
    <EnglishText />
    <Notes />
    <Id>80</Id>
    <Status />
  </Entry>
  <Entry>
    <PointerOffsetDec>1400</PointerOffsetDec>
    <PointerOffsetHex>0x578</PointerOffsetHex>
    <JapaneseText>大角豆に酢をかけサシスセソ</JapaneseText>
    <EnglishText />
    <Notes />
    <Id>81</Id>
    <Status />
  </Entry>
  <Entry>
    <PointerOffsetDec>1428</PointerOffsetDec>
    <PointerOffsetHex>0x594</PointerOffsetHex>
    <JapaneseText>ウンチク。</JapaneseText>
    <EnglishText />
    <Notes />
    <Id>82</Id>
    <Status />
  </Entry>
  <Entry>
    <PointerOffsetDec>1441</PointerOffsetDec>
    <PointerOffsetHex>0x5a1</PointerOffsetHex>
    <JapaneseText>あめんぼ赤いなアイウエオ</JapaneseText>
    <EnglishText />
    <Notes />
    <Id>83</Id>
    <Status />
  </Entry>
  <Entry>
    <PointerOffsetDec>1467</PointerOffsetDec>
    <PointerOffsetHex>0x5bb</PointerOffsetHex>
    <JapaneseText>柿木栗の木カキクケコ</JapaneseText>
    <EnglishText />
    <Notes />
    <Id>84</Id>
    <Status />
  </Entry>
  <Entry>
    <PointerOffsetDec>1489</PointerOffsetDec>
    <PointerOffsetHex>0x5d1</PointerOffsetHex>
    <JapaneseText>大角豆に酢をかけサシスセソ</JapaneseText>
    <EnglishText />
    <Notes />
    <Id>85</Id>
    <Status />
  </Entry>
  <Entry>
    <PointerOffsetDec>1517</PointerOffsetDec>
    <PointerOffsetHex>0x5ed</PointerOffsetHex>
    <JapaneseText>超喜び。</JapaneseText>
    <EnglishText />
    <Notes />
    <Id>86</Id>
    <Status />
  </Entry>
  <Entry>
    <PointerOffsetDec>1528</PointerOffsetDec>
    <PointerOffsetHex>0x5f8</PointerOffsetHex>
    <JapaneseText>あめんぼ赤いなアイウエオ</JapaneseText>
    <EnglishText />
    <Notes />
    <Id>87</Id>
    <Status />
  </Entry>
  <Entry>
    <PointerOffsetDec>1554</PointerOffsetDec>
    <PointerOffsetHex>0x612</PointerOffsetHex>
    <JapaneseText>柿木栗の木カキクケコ</JapaneseText>
    <EnglishText />
    <Notes />
    <Id>88</Id>
    <Status />
  </Entry>
  <Entry>
    <PointerOffsetDec>1576</PointerOffsetDec>
    <PointerOffsetHex>0x628</PointerOffsetHex>
    <JapaneseText>大角豆に酢をかけサシスセソ</JapaneseText>
    <EnglishText />
    <Notes />
    <Id>89</Id>
    <Status />
  </Entry>
  <Entry>
    <PointerOffsetDec>1604</PointerOffsetDec>
    <PointerOffsetHex>0x644</PointerOffsetHex>
    <JapaneseText>通常。</JapaneseText>
    <EnglishText />
    <Notes />
    <Id>90</Id>
    <Status />
  </Entry>
  <Entry>
    <PointerOffsetDec>1613</PointerOffsetDec>
    <PointerOffsetHex>0x64d</PointerOffsetHex>
    <JapaneseText>あめんぼ赤いなアイウエオ</JapaneseText>
    <EnglishText />
    <Notes />
    <Id>91</Id>
    <Status />
  </Entry>
  <Entry>
    <PointerOffsetDec>1639</PointerOffsetDec>
    <PointerOffsetHex>0x667</PointerOffsetHex>
    <JapaneseText>柿木栗の木カキクケコ</JapaneseText>
    <EnglishText />
    <Notes />
    <Id>92</Id>
    <Status />
  </Entry>
  <Entry>
    <PointerOffsetDec>1661</PointerOffsetDec>
    <PointerOffsetHex>0x67d</PointerOffsetHex>
    <JapaneseText>大角豆に酢をかけサシスセソ</JapaneseText>
    <EnglishText />
    <Notes />
    <Id>93</Id>
    <Status />
  </Entry>
  <Entry>
    <PointerOffsetDec>1689</PointerOffsetDec>
    <PointerOffsetHex>0x699</PointerOffsetHex>
    <JapaneseText>笑い。</JapaneseText>
    <EnglishText />
    <Notes />
    <Id>94</Id>
    <Status />
  </Entry>
  <Entry>
    <PointerOffsetDec>1698</PointerOffsetDec>
    <PointerOffsetHex>0x6a2</PointerOffsetHex>
    <JapaneseText>あめんぼ赤いなアイウエオ</JapaneseText>
    <EnglishText />
    <Notes />
    <Id>95</Id>
    <Status />
  </Entry>
  <Entry>
    <PointerOffsetDec>1724</PointerOffsetDec>
    <PointerOffsetHex>0x6bc</PointerOffsetHex>
    <JapaneseText>柿木栗の木カキクケコ</JapaneseText>
    <EnglishText />
    <Notes />
    <Id>96</Id>
    <Status />
  </Entry>
  <Entry>
    <PointerOffsetDec>1746</PointerOffsetDec>
    <PointerOffsetHex>0x6d2</PointerOffsetHex>
    <JapaneseText>大角豆に酢をかけサシスセソ</JapaneseText>
    <EnglishText />
    <Notes />
    <Id>97</Id>
    <Status />
  </Entry>
  <Entry>
    <PointerOffsetDec>1774</PointerOffsetDec>
    <PointerOffsetHex>0x6ee</PointerOffsetHex>
    <JapaneseText>怒り。</JapaneseText>
    <EnglishText />
    <Notes />
    <Id>98</Id>
    <Status />
  </Entry>
  <Entry>
    <PointerOffsetDec>1783</PointerOffsetDec>
    <PointerOffsetHex>0x6f7</PointerOffsetHex>
    <JapaneseText>あめんぼ赤いなアイウエオ</JapaneseText>
    <EnglishText />
    <Notes />
    <Id>99</Id>
    <Status />
  </Entry>
  <Entry>
    <PointerOffsetDec>1809</PointerOffsetDec>
    <PointerOffsetHex>0x711</PointerOffsetHex>
    <JapaneseText>柿木栗の木カキクケコ</JapaneseText>
    <EnglishText />
    <Notes />
    <Id>100</Id>
    <Status />
  </Entry>
  <Entry>
    <PointerOffsetDec>1831</PointerOffsetDec>
    <PointerOffsetHex>0x727</PointerOffsetHex>
    <JapaneseText>大角豆に酢をかけサシスセソ</JapaneseText>
    <EnglishText />
    <Notes />
    <Id>101</Id>
    <Status />
  </Entry>
  <Entry>
    <PointerOffsetDec>1859</PointerOffsetDec>
    <PointerOffsetHex>0x743</PointerOffsetHex>
    <JapaneseText>ウンチク。</JapaneseText>
    <EnglishText />
    <Notes />
    <Id>102</Id>
    <Status />
  </Entry>
  <Entry>
    <PointerOffsetDec>1872</PointerOffsetDec>
    <PointerOffsetHex>0x750</PointerOffsetHex>
    <JapaneseText>あめんぼ赤いなアイウエオ</JapaneseText>
    <EnglishText />
    <Notes />
    <Id>103</Id>
    <Status />
  </Entry>
  <Entry>
    <PointerOffsetDec>1898</PointerOffsetDec>
    <PointerOffsetHex>0x76a</PointerOffsetHex>
    <JapaneseText>柿木栗の木カキクケコ</JapaneseText>
    <EnglishText />
    <Notes />
    <Id>104</Id>
    <Status />
  </Entry>
  <Entry>
    <PointerOffsetDec>1920</PointerOffsetDec>
    <PointerOffsetHex>0x780</PointerOffsetHex>
    <JapaneseText>大角豆に酢をかけサシスセソ</JapaneseText>
    <EnglishText />
    <Notes />
    <Id>105</Id>
    <Status />
  </Entry>
  <Entry>
    <PointerOffsetDec>1948</PointerOffsetDec>
    <PointerOffsetHex>0x79c</PointerOffsetHex>
    <JapaneseText>超喜び。</JapaneseText>
    <EnglishText />
    <Notes />
    <Id>106</Id>
    <Status />
  </Entry>
  <Entry>
    <PointerOffsetDec>1959</PointerOffsetDec>
    <PointerOffsetHex>0x7a7</PointerOffsetHex>
    <JapaneseText>あめんぼ赤いなアイウエオ</JapaneseText>
    <EnglishText />
    <Notes />
    <Id>107</Id>
    <Status />
  </Entry>
  <Entry>
    <PointerOffsetDec>1985</PointerOffsetDec>
    <PointerOffsetHex>0x7c1</PointerOffsetHex>
    <JapaneseText>柿木栗の木カキクケコ</JapaneseText>
    <EnglishText />
    <Notes />
    <Id>108</Id>
    <Status />
  </Entry>
  <Entry>
    <PointerOffsetDec>2007</PointerOffsetDec>
    <PointerOffsetHex>0x7d7</PointerOffsetHex>
    <JapaneseText>大角豆に酢をかけサシスセソ</JapaneseText>
    <EnglishText />
    <Notes />
    <Id>109</Id>
    <Status />
  </Entry>
</Entries>