<?xml version='1.0' encoding='utf-8'?>
<Entries>
  <Entry>
    <PointerOffsetDec>982</PointerOffsetDec>
    <PointerOffsetHex>0x3d6</PointerOffsetHex>
    <JapaneseText>さて、あなた達。</JapaneseText>
    <EnglishText />
    <Notes />
    <Id>67</Id>
    <Status />
  </Entry>
  <Entry>
    <PointerOffsetDec>1000</PointerOffsetDec>
    <PointerOffsetHex>0x3e8</PointerOffsetHex>
    <JapaneseText>もし良かったら、話を聞いてもいい？</JapaneseText>
    <EnglishText />
    <Notes />
    <Id>68</Id>
    <Status />
  </Entry>
  <Entry>
    <PointerOffsetDec>1035</PointerOffsetDec>
    <PointerOffsetHex>0x40b</PointerOffsetHex>
    <JapaneseText>その前に自己紹介をしなくちゃね</JapaneseText>
    <EnglishText />
    <Notes />
    <Id>69</Id>
    <Status />
  </Entry>
  <Entry>
    <PointerOffsetDec>1066</PointerOffsetDec>
    <PointerOffsetHex>0x42a</PointerOffsetHex>
    <JapaneseText>わたしは、アンジュ。</JapaneseText>
    <EnglishText />
    <Notes />
    <Id>70</Id>
    <Status />
  </Entry>
  <Entry>
    <PointerOffsetDec>1088</PointerOffsetDec>
    <PointerOffsetHex>0x440</PointerOffsetHex>
    <JapaneseText>このギルド、アドリビトムのリーダーよ</JapaneseText>
    <EnglishText />
    <Notes />
    <Id>71</Id>
    <Status />
  </Entry>
  <Entry>
    <PointerOffsetDec>1125</PointerOffsetDec>
    <PointerOffsetHex>0x465</PointerOffsetHex>
    <JapaneseText>申し遅れました。</JapaneseText>
    <EnglishText />
    <Notes />
    <Id>72</Id>
    <Status />
  </Entry>
  <Entry>
    <PointerOffsetDec>1143</PointerOffsetDec>
    <PointerOffsetHex>0x477</PointerOffsetHex>
    <JapaneseText>わたしは、ガルバンゾ国の王女エステリーゼ。</JapaneseText>
    <EnglishText />
    <Notes />
    <Id>73</Id>
    <Status />
  </Entry>
  <Entry>
    <PointerOffsetDec>1187</PointerOffsetDec>
    <PointerOffsetHex>0x4a3</PointerOffsetHex>
    <JapaneseText>エステル、って呼んで下さい</JapaneseText>
    <EnglishText />
    <Notes />
    <Id>74</Id>
    <Status />
  </Entry>
  <Entry>
    <PointerOffsetDec>1214</PointerOffsetDec>
    <PointerOffsetHex>0x4be</PointerOffsetHex>
    <JapaneseText>ええと、あなたの名は</JapaneseText>
    <EnglishText />
    <Notes />
    <Id>75</Id>
    <Status />
  </Entry>
  <Entry>
    <PointerOffsetDec>1236</PointerOffsetDec>
    <PointerOffsetHex>0x4d4</PointerOffsetHex>
    <JapaneseText>○○でしたね</JapaneseText>
    <EnglishText />
    <Notes />
    <Id>76</Id>
    <Status />
  </Entry>
  <Entry>
    <PointerOffsetDec>1249</PointerOffsetDec>
    <PointerOffsetHex>0x4e1</PointerOffsetHex>
    <JapaneseText>助けていただいて、ありがとうございます</JapaneseText>
    <EnglishText />
    <Notes />
    <Id>77</Id>
    <Status />
  </Entry>
  <Entry>
    <PointerOffsetDec>1288</PointerOffsetDec>
    <PointerOffsetHex>0x508</PointerOffsetHex>
    <JapaneseText>あたしは、リタ・モルディオ</JapaneseText>
    <EnglishText />
    <Notes />
    <Id>78</Id>
    <Status />
  </Entry>
  <Entry>
    <PointerOffsetDec>1315</PointerOffsetDec>
    <PointerOffsetHex>0x523</PointerOffsetHex>
    <JapaneseText>オレはユーリ・ローウェル。</JapaneseText>
    <EnglishText />
    <Notes />
    <Id>79</Id>
    <Status />
  </Entry>
  <Entry>
    <PointerOffsetDec>1343</PointerOffsetDec>
    <PointerOffsetHex>0x53f</PointerOffsetHex>
    <JapaneseText>ガルバンゾ国のギルドの者だ</JapaneseText>
    <EnglishText />
    <Notes />
    <Id>80</Id>
    <Status />
  </Entry>
  <Entry>
    <PointerOffsetDec>1370</PointerOffsetDec>
    <PointerOffsetHex>0x55a</PointerOffsetHex>
    <JapaneseText>今は、このお姫様に</JapaneseText>
    <EnglishText />
    <Notes />
    <Id>81</Id>
    <Status />
  </Entry>
  <Entry>
    <PointerOffsetDec>1390</PointerOffsetDec>
    <PointerOffsetHex>0x56e</PointerOffsetHex>
    <JapaneseText>旅の護衛として雇われている</JapaneseText>
    <EnglishText />
    <Notes />
    <Id>82</Id>
    <Status />
  </Entry>
  <Entry>
    <PointerOffsetDec>1417</PointerOffsetDec>
    <PointerOffsetHex>0x589</PointerOffsetHex>
    <JapaneseText>あなたの様な大国の王族がなぜ、</JapaneseText>
    <EnglishText />
    <Notes />
    <Id>83</Id>
    <Status />
  </Entry>
  <Entry>
    <PointerOffsetDec>1449</PointerOffsetDec>
    <PointerOffsetHex>0x5a9</PointerOffsetHex>
    <JapaneseText>ギルドを雇って旅なんてしているの？</JapaneseText>
    <EnglishText />
    <Notes />
    <Id>84</Id>
    <Status />
  </Entry>
  <Entry>
    <PointerOffsetDec>1484</PointerOffsetDec>
    <PointerOffsetHex>0x5cc</PointerOffsetHex>
    <JapaneseText>コンフェイト大森林には、ガルバンゾ国の</JapaneseText>
    <EnglishText />
    <Notes />
    <Id>85</Id>
    <Status />
  </Entry>
  <Entry>
    <PointerOffsetDec>1524</PointerOffsetDec>
    <PointerOffsetHex>0x5f4</PointerOffsetHex>
    <JapaneseText>星晶採掘地があるんです</JapaneseText>
    <EnglishText />
    <Notes />
    <Id>86</Id>
    <Status />
  </Entry>
  <Entry>
    <PointerOffsetDec>1547</PointerOffsetDec>
    <PointerOffsetHex>0x60b</PointerOffsetHex>
    <JapaneseText>現在、ウリズン帝国とその土地をめぐって</JapaneseText>
    <EnglishText />
    <Notes />
    <Id>87</Id>
    <Status />
  </Entry>
  <Entry>
    <PointerOffsetDec>1587</PointerOffsetDec>
    <PointerOffsetHex>0x633</PointerOffsetHex>
    <JapaneseText>緊張状態なのですが…</JapaneseText>
    <EnglishText />
    <Notes />
    <Id>88</Id>
    <Status />
  </Entry>
  <Entry>
    <PointerOffsetDec>1608</PointerOffsetDec>
    <PointerOffsetHex>0x648</PointerOffsetHex>
    <JapaneseText>その採掘地で今、</JapaneseText>
    <EnglishText />
    <Notes />
    <Id>89</Id>
    <Status />
  </Entry>
  <Entry>
    <PointerOffsetDec>1626</PointerOffsetDec>
    <PointerOffsetHex>0x65a</PointerOffsetHex>
    <JapaneseText>変な現象が起こっているという話を</JapaneseText>
    <EnglishText />
    <Notes />
    <Id>90</Id>
    <Status />
  </Entry>
  <Entry>
    <PointerOffsetDec>1660</PointerOffsetDec>
    <PointerOffsetHex>0x67c</PointerOffsetHex>
    <JapaneseText>聞いたんです</JapaneseText>
    <EnglishText />
    <Notes />
    <Id>91</Id>
    <Status />
  </Entry>
  <Entry>
    <PointerOffsetDec>1673</PointerOffsetDec>
    <PointerOffsetHex>0x689</PointerOffsetHex>
    <JapaneseText>変な現象？</JapaneseText>
    <EnglishText />
    <Notes />
    <Id>92</Id>
    <Status />
  </Entry>
  <Entry>
    <PointerOffsetDec>1684</PointerOffsetDec>
    <PointerOffsetHex>0x694</PointerOffsetHex>
    <JapaneseText>採掘が行われた土地の生物が、</JapaneseText>
    <EnglishText />
    <Notes />
    <Id>93</Id>
    <Status />
  </Entry>
  <Entry>
    <PointerOffsetDec>1714</PointerOffsetDec>
    <PointerOffsetHex>0x6b2</PointerOffsetHex>
    <JapaneseText>変化してるって話よ</JapaneseText>
    <EnglishText />
    <Notes />
    <Id>94</Id>
    <Status />
  </Entry>
  <Entry>
    <PointerOffsetDec>1733</PointerOffsetDec>
    <PointerOffsetHex>0x6c5</PointerOffsetHex>
    <JapaneseText>どんな変化が起こってるかってのは、</JapaneseText>
    <EnglishText />
    <Notes />
    <Id>95</Id>
    <Status />
  </Entry>
  <Entry>
    <PointerOffsetDec>1769</PointerOffsetDec>
    <PointerOffsetHex>0x6e9</PointerOffsetHex>
    <JapaneseText>明確にわかってるわけじゃないけど</JapaneseText>
    <EnglishText />
    <Notes />
    <Id>96</Id>
    <Status />
  </Entry>
  <Entry>
    <PointerOffsetDec>1803</PointerOffsetDec>
    <PointerOffsetHex>0x70b</PointerOffsetHex>
    <JapaneseText>採掘者の間でそんな話が上がってて</JapaneseText>
    <EnglishText />
    <Notes />
    <Id>97</Id>
    <Status />
  </Entry>
  <Entry>
    <PointerOffsetDec>1836</PointerOffsetDec>
    <PointerOffsetHex>0x72c</PointerOffsetHex>
    <JapaneseText>それを聞いた学者が「土地にある星晶を</JapaneseText>
    <EnglishText />
    <Notes />
    <Id>98</Id>
    <Status />
  </Entry>
  <Entry>
    <PointerOffsetDec>1874</PointerOffsetDec>
    <PointerOffsetHex>0x752</PointerOffsetHex>
    <JapaneseText>取り過ぎたせいではないか」って</JapaneseText>
    <EnglishText />
    <Notes />
    <Id>99</Id>
    <Status />
  </Entry>
  <Entry>
    <PointerOffsetDec>1906</PointerOffsetDec>
    <PointerOffsetHex>0x772</PointerOffsetHex>
    <JapaneseText>仮説を立てて、騒ぎ始めたのよ</JapaneseText>
    <EnglishText />
    <Notes />
    <Id>100</Id>
    <Status />
  </Entry>
  <Entry>
    <PointerOffsetDec>1935</PointerOffsetDec>
    <PointerOffsetHex>0x78f</PointerOffsetHex>
    <JapaneseText>でも、それに対して国の評議会は何も</JapaneseText>
    <EnglishText />
    <Notes />
    <Id>101</Id>
    <Status />
  </Entry>
  <Entry>
    <PointerOffsetDec>1971</PointerOffsetDec>
    <PointerOffsetHex>0x7b3</PointerOffsetHex>
    <JapaneseText>調査をせず、ついには世間を騒がせた罪で</JapaneseText>
    <EnglishText />
    <Notes />
    <Id>102</Id>
    <Status />
  </Entry>
  <Entry>
    <PointerOffsetDec>2011</PointerOffsetDec>
    <PointerOffsetHex>0x7db</PointerOffsetHex>
    <JapaneseText>学者まで逮捕、ってわけ</JapaneseText>
    <EnglishText />
    <Notes />
    <Id>103</Id>
    <Status />
  </Entry>
  <Entry>
    <PointerOffsetDec>2034</PointerOffsetDec>
    <PointerOffsetHex>0x7f2</PointerOffsetHex>
    <JapaneseText>その話を知って、わたし、</JapaneseText>
    <EnglishText />
    <Notes />
    <Id>104</Id>
    <Status />
  </Entry>
  <Entry>
    <PointerOffsetDec>2060</PointerOffsetDec>
    <PointerOffsetHex>0x80c</PointerOffsetHex>
    <JapaneseText>本当の事が知りたくて</JapaneseText>
    <EnglishText />
    <Notes />
    <Id>105</Id>
    <Status />
  </Entry>
  <Entry>
    <PointerOffsetDec>2081</PointerOffsetDec>
    <PointerOffsetHex>0x821</PointerOffsetHex>
    <JapaneseText>国が動かないのなら、まず自分で調査を</JapaneseText>
    <EnglishText />
    <Notes />
    <Id>106</Id>
    <Status />
  </Entry>
  <Entry>
    <PointerOffsetDec>2119</PointerOffsetDec>
    <PointerOffsetHex>0x847</PointerOffsetHex>
    <JapaneseText>しようと国を出たんです</JapaneseText>
    <EnglishText />
    <Notes />
    <Id>107</Id>
    <Status />
  </Entry>
  <Entry>
    <PointerOffsetDec>2142</PointerOffsetDec>
    <PointerOffsetHex>0x85e</PointerOffsetHex>
    <JapaneseText>そこまでは良かったんだが。</JapaneseText>
    <EnglishText />
    <Notes />
    <Id>108</Id>
    <Status />
  </Entry>
  <Entry>
    <PointerOffsetDec>2170</PointerOffsetDec>
    <PointerOffsetHex>0x87a</PointerOffsetHex>
    <JapaneseText>森で迷うわ、あのサレって奴に</JapaneseText>
    <EnglishText />
    <Notes />
    <Id>109</Id>
    <Status />
  </Entry>
  <Entry>
    <PointerOffsetDec>2200</PointerOffsetDec>
    <PointerOffsetHex>0x898</PointerOffsetHex>
    <JapaneseText>エステルがさらわれるわでな</JapaneseText>
    <EnglishText />
    <Notes />
    <Id>110</Id>
    <Status />
  </Entry>
  <Entry>
    <PointerOffsetDec>2227</PointerOffsetDec>
    <PointerOffsetHex>0x8b3</PointerOffsetHex>
    <JapaneseText>サレの所属するウリズン帝国と</JapaneseText>
    <EnglishText />
    <Notes />
    <Id>111</Id>
    <Status />
  </Entry>
  <Entry>
    <PointerOffsetDec>2257</PointerOffsetDec>
    <PointerOffsetHex>0x8d1</PointerOffsetHex>
    <JapaneseText>あなたのガルバンゾ国は、今星晶を巡って</JapaneseText>
    <EnglishText />
    <Notes />
    <Id>112</Id>
    <Status />
  </Entry>
  <Entry>
    <PointerOffsetDec>2297</PointerOffsetDec>
    <PointerOffsetHex>0x8f9</PointerOffsetHex>
    <JapaneseText>緊張状態にあるものね…</JapaneseText>
    <EnglishText />
    <Notes />
    <Id>113</Id>
    <Status />
  </Entry>
  <Entry>
    <PointerOffsetDec>2320</PointerOffsetDec>
    <PointerOffsetHex>0x910</PointerOffsetHex>
    <JapaneseText>コンフェイト大森林の辺りは、様々な国が</JapaneseText>
    <EnglishText />
    <Notes />
    <Id>114</Id>
    <Status />
  </Entry>
  <Entry>
    <PointerOffsetDec>2360</PointerOffsetDec>
    <PointerOffsetHex>0x938</PointerOffsetHex>
    <JapaneseText>星晶採掘に関わっていますし…</JapaneseText>
    <EnglishText />
    <Notes />
    <Id>115</Id>
    <Status />
  </Entry>
  <Entry>
    <PointerOffsetDec>2389</PointerOffsetDec>
    <PointerOffsetHex>0x955</PointerOffsetHex>
    <JapaneseText>早く、問題の採掘地へ急がないと…</JapaneseText>
    <EnglishText />
    <Notes />
    <Id>116</Id>
    <Status />
  </Entry>
  <Entry>
    <PointerOffsetDec>2422</PointerOffsetDec>
    <PointerOffsetHex>0x976</PointerOffsetHex>
    <JapaneseText>焦っては、駄目。</JapaneseText>
    <EnglishText />
    <Notes />
    <Id>117</Id>
    <Status />
  </Entry>
  <Entry>
    <PointerOffsetDec>2440</PointerOffsetDec>
    <PointerOffsetHex>0x988</PointerOffsetHex>
    <JapaneseText>まず、あなた達には休養が必要よ</JapaneseText>
    <EnglishText />
    <Notes />
    <Id>118</Id>
    <Status />
  </Entry>
  <Entry>
    <PointerOffsetDec>2471</PointerOffsetDec>
    <PointerOffsetHex>0x9a7</PointerOffsetHex>
    <JapaneseText>わたし達も何か手伝えそうだから、</JapaneseText>
    <EnglishText />
    <Notes />
    <Id>119</Id>
    <Status />
  </Entry>
  <Entry>
    <PointerOffsetDec>2505</PointerOffsetDec>
    <PointerOffsetHex>0x9c9</PointerOffsetHex>
    <JapaneseText>今はゆっくりくつろいでいて</JapaneseText>
    <EnglishText />
    <Notes />
    <Id>120</Id>
    <Status />
  </Entry>
  <Entry>
    <PointerOffsetDec>2532</PointerOffsetDec>
    <PointerOffsetHex>0x9e4</PointerOffsetHex>
    <JapaneseText>はい。</JapaneseText>
    <EnglishText />
    <Notes />
    <Id>121</Id>
    <Status />
  </Entry>
  <Entry>
    <PointerOffsetDec>2540</PointerOffsetDec>
    <PointerOffsetHex>0x9ec</PointerOffsetHex>
    <JapaneseText>そうさせていただきます</JapaneseText>
    <EnglishText />
    <Notes />
    <Id>122</Id>
    <Status />
  </Entry>
</Entries>