<SceneText>
  <FriendlyName></FriendlyName>
  <Speakers/>
    <Section></Section>
  <Entries>
    <Entry>
      <PointerOffset>500</PointerOffset>
      <JapaneseText>なぁ、これ綺麗よ！</JapaneseText>
      <EnglishText/>
      <Notes/>
      <Id>33</Id>
      <Status>To Do</Status>
    </Entry>
    <Entry>
      <PointerOffset>520</PointerOffset>
      <JapaneseText>見て見て〜</JapaneseText>
      <EnglishText/>
      <Notes/>
      <Id>34</Id>
      <Status>To Do</Status>
    </Entry>
    <Entry>
      <PointerOffset>531</PointerOffset>
      <JapaneseText>うわぁ……綺麗な石ですねぇ！</JapaneseText>
      <EnglishText/>
      <Notes/>
      <Id>35</Id>
      <Status>To Do</Status>
    </Entry>
    <Entry>
      <PointerOffset>560</PointerOffset>
      <JapaneseText>ほんとだね。</JapaneseText>
      <EnglishText/>
      <Notes/>
      <Id>36</Id>
      <Status>To Do</Status>
    </Entry>
    <Entry>
      <PointerOffset>574</PointerOffset>
      <JapaneseText>透きとおってて……。</JapaneseText>
      <EnglishText/>
      <Notes/>
      <Id>37</Id>
      <Status>To Do</Status>
    </Entry>
    <Entry>
      <PointerOffset>596</PointerOffset>
      <JapaneseText>光の加減で、色んな色に見える</JapaneseText>
      <EnglishText/>
      <Notes/>
      <Id>38</Id>
      <Status>To Do</Status>
    </Entry>
    <Entry>
      <PointerOffset>625</PointerOffset>
      <JapaneseText>メルディ、知ってる。</JapaneseText>
      <EnglishText/>
      <Notes/>
      <Id>39</Id>
      <Status>To Do</Status>
    </Entry>
    <Entry>
      <PointerOffset>647</PointerOffset>
      <JapaneseText>これ、天使の羽って言うよー</JapaneseText>
      <EnglishText/>
      <Notes/>
      <Id>40</Id>
      <Status>To Do</Status>
    </Entry>
    <Entry>
      <PointerOffset>674</PointerOffset>
      <JapaneseText>天使の羽？</JapaneseText>
      <EnglishText/>
      <Notes/>
      <Id>41</Id>
      <Status>To Do</Status>
    </Entry>
    <Entry>
      <PointerOffset>686</PointerOffset>
      <JapaneseText>石なのに、羽って呼ぶの？</JapaneseText>
      <EnglishText/>
      <Notes/>
      <Id>42</Id>
      <Status>To Do</Status>
    </Entry>
    <Entry>
      <PointerOffset>711</PointerOffset>
      <JapaneseText>はいな。</JapaneseText>
      <EnglishText/>
      <Notes/>
      <Id>43</Id>
      <Status>To Do</Status>
    </Entry>
    <Entry>
      <PointerOffset>721</PointerOffset>
      <JapaneseText>ホンモノが羽みたいにキラキラして</JapaneseText>
      <EnglishText/>
      <Notes/>
      <Id>44</Id>
      <Status>To Do</Status>
    </Entry>
    <Entry>
      <PointerOffset>755</PointerOffset>
      <JapaneseText>綺麗な石、そう言うよー</JapaneseText>
      <EnglishText/>
      <Notes/>
      <Id>45</Id>
      <Status>To Do</Status>
    </Entry>
    <Entry>
      <PointerOffset>778</PointerOffset>
      <JapaneseText>天使ですか……。</JapaneseText>
      <EnglishText/>
      <Notes/>
      <Id>46</Id>
      <Status>To Do</Status>
    </Entry>
    <Entry>
      <PointerOffset>796</PointerOffset>
      <JapaneseText>以前は、人間と天使が一緒に</JapaneseText>
      <EnglishText/>
      <Notes/>
      <Id>47</Id>
      <Status>To Do</Status>
    </Entry>
    <Entry>
      <PointerOffset>824</PointerOffset>
      <JapaneseText>生活していたそうですから</JapaneseText>
      <EnglishText/>
      <Notes/>
      <Id>48</Id>
      <Status>To Do</Status>
    </Entry>
    <Entry>
      <PointerOffset>849</PointerOffset>
      <JapaneseText>それで、そういう言い回しが</JapaneseText>
      <EnglishText/>
      <Notes/>
      <Id>49</Id>
      <Status>To Do</Status>
    </Entry>
    <Entry>
      <PointerOffset>877</PointerOffset>
      <JapaneseText>生まれたのかもしれないですね</JapaneseText>
      <EnglishText/>
      <Notes/>
      <Id>50</Id>
      <Status>To Do</Status>
    </Entry>
    <Entry>
      <PointerOffset>906</PointerOffset>
      <JapaneseText>そっか。</JapaneseText>
      <EnglishText/>
      <Notes/>
      <Id>51</Id>
      <Status>To Do</Status>
    </Entry>
    <Entry>
      <PointerOffset>916</PointerOffset>
      <JapaneseText>ヒトや、国や、</JapaneseText>
      <EnglishText/>
      <Notes/>
      <Id>52</Id>
      <Status>To Do</Status>
    </Entry>
    <Entry>
      <PointerOffset>932</PointerOffset>
      <JapaneseText>世界が変わっても……</JapaneseText>
      <EnglishText/>
      <Notes/>
      <Id>53</Id>
      <Status>To Do</Status>
    </Entry>
    <Entry>
      <PointerOffset>953</PointerOffset>
      <JapaneseText>変わらずに残るものも、あるんだね</JapaneseText>
      <EnglishText/>
      <Notes/>
      <Id>54</Id>
      <Status>To Do</Status>
    </Entry>
    <Entry>
      <PointerOffset>986</PointerOffset>
      <JapaneseText>ワイール！</JapaneseText>
      <EnglishText/>
      <Notes/>
      <Id>55</Id>
      <Status>To Do</Status>
    </Entry>
    <Entry>
      <PointerOffset>998</PointerOffset>
      <JapaneseText>なんだか、フシギな気分なるよー</JapaneseText>
      <EnglishText/>
      <Notes/>
      <Id>56</Id>
      <Status>To Do</Status>
    </Entry>
  </Entries>
</SceneText>