<SceneText>
  <FriendlyName></FriendlyName>
  <Speakers/>
    <Section></Section>
  <Entries>
    <Entry>
      <PointerOffset>38</PointerOffset>
      <JapaneseText>傲</JapaneseText>
      <EnglishText/>
      <Notes/>
      <Id>3</Id>
      <Status>To Do</Status>
    </Entry>
    <Entry>
      <PointerOffset>730</PointerOffset>
      <JapaneseText>あ……！</JapaneseText>
      <EnglishText/>
      <Notes/>
      <Id>50</Id>
      <Status>To Do</Status>
    </Entry>
    <Entry>
      <PointerOffset>740</PointerOffset>
      <JapaneseText>ちょっと待って、カイウス！</JapaneseText>
      <EnglishText/>
      <Notes/>
      <Id>51</Id>
      <Status>To Do</Status>
    </Entry>
    <Entry>
      <PointerOffset>767</PointerOffset>
      <JapaneseText>何だ、ジーニアスか</JapaneseText>
      <EnglishText/>
      <Notes/>
      <Id>52</Id>
      <Status>To Do</Status>
    </Entry>
    <Entry>
      <PointerOffset>786</PointerOffset>
      <JapaneseText>どうしたんだよ？</JapaneseText>
      <EnglishText/>
      <Notes/>
      <Id>53</Id>
      <Status>To Do</Status>
    </Entry>
    <Entry>
      <PointerOffset>804</PointerOffset>
      <JapaneseText>眉間にシワが寄ってるぜ？</JapaneseText>
      <EnglishText/>
      <Notes/>
      <Id>54</Id>
      <Status>To Do</Status>
    </Entry>
    <Entry>
      <PointerOffset>829</PointerOffset>
      <JapaneseText>もう……茶化さないでよ</JapaneseText>
      <EnglishText/>
      <Notes/>
      <Id>55</Id>
      <Status>To Do</Status>
    </Entry>
    <Entry>
      <PointerOffset>852</PointerOffset>
      <JapaneseText>……ほら、この間キミの事</JapaneseText>
      <EnglishText/>
      <Notes/>
      <Id>56</Id>
      <Status>To Do</Status>
    </Entry>
    <Entry>
      <PointerOffset>878</PointerOffset>
      <JapaneseText>色々教えてもらったでしょ？</JapaneseText>
      <EnglishText/>
      <Notes/>
      <Id>57</Id>
      <Status>To Do</Status>
    </Entry>
    <Entry>
      <PointerOffset>905</PointerOffset>
      <JapaneseText>ボク、その時に</JapaneseText>
      <EnglishText/>
      <Notes/>
      <Id>58</Id>
      <Status>To Do</Status>
    </Entry>
    <Entry>
      <PointerOffset>921</PointerOffset>
      <JapaneseText>「リカンツってすごいね！」って</JapaneseText>
      <EnglishText/>
      <Notes/>
      <Id>59</Id>
      <Status>To Do</Status>
    </Entry>
    <Entry>
      <PointerOffset>953</PointerOffset>
      <JapaneseText>言っちゃったけど……嫌じゃなかった？</JapaneseText>
      <EnglishText/>
      <Notes/>
      <Id>60</Id>
      <Status>To Do</Status>
    </Entry>
    <Entry>
      <PointerOffset>990</PointerOffset>
      <JapaneseText>嫌？　</JapaneseText>
      <EnglishText/>
      <Notes/>
      <Id>61</Id>
      <Status>To Do</Status>
    </Entry>
    <Entry>
      <PointerOffset>998</PointerOffset>
      <JapaneseText>何でだ？</JapaneseText>
      <EnglishText/>
      <Notes/>
      <Id>62</Id>
      <Status>To Do</Status>
    </Entry>
    <Entry>
      <PointerOffset>1007</PointerOffset>
      <JapaneseText>聞いたんだ。その……リカンツって</JapaneseText>
      <EnglishText/>
      <Notes/>
      <Id>63</Id>
      <Status>To Do</Status>
    </Entry>
    <Entry>
      <PointerOffset>1041</PointerOffset>
      <JapaneseText>カイウス達の種族をバカにして</JapaneseText>
      <EnglishText/>
      <Notes/>
      <Id>64</Id>
      <Status>To Do</Status>
    </Entry>
    <Entry>
      <PointerOffset>1071</PointerOffset>
      <JapaneseText>呼ぶ時の言い方だったって……</JapaneseText>
      <EnglishText/>
      <Notes/>
      <Id>65</Id>
      <Status>To Do</Status>
    </Entry>
    <Entry>
      <PointerOffset>1100</PointerOffset>
      <JapaneseText>ああ……そういう事か</JapaneseText>
      <EnglishText/>
      <Notes/>
      <Id>66</Id>
      <Status>To Do</Status>
    </Entry>
    <Entry>
      <PointerOffset>1121</PointerOffset>
      <JapaneseText>確かに、昔はそうだったみたいだな。</JapaneseText>
      <EnglishText/>
      <Notes/>
      <Id>67</Id>
      <Status>To Do</Status>
    </Entry>
    <Entry>
      <PointerOffset>1157</PointerOffset>
      <JapaneseText>オレ達は珍しい種族みたいだし……</JapaneseText>
      <EnglishText/>
      <Notes/>
      <Id>68</Id>
      <Status>To Do</Status>
    </Entry>
    <Entry>
      <PointerOffset>1191</PointerOffset>
      <JapaneseText>他の奴から見たら、気味悪く思えたんだろ</JapaneseText>
      <EnglishText/>
      <Notes/>
      <Id>69</Id>
      <Status>To Do</Status>
    </Entry>
    <Entry>
      <PointerOffset>1230</PointerOffset>
      <JapaneseText>気味悪くなんてないよ！</JapaneseText>
      <EnglishText/>
      <Notes/>
      <Id>70</Id>
      <Status>To Do</Status>
    </Entry>
    <Entry>
      <PointerOffset>1253</PointerOffset>
      <JapaneseText>ボクは……そういうの嫌なんだ。</JapaneseText>
      <EnglishText/>
      <Notes/>
      <Id>71</Id>
      <Status>To Do</Status>
    </Entry>
    <Entry>
      <PointerOffset>1285</PointerOffset>
      <JapaneseText>種族で、自分の価値まで</JapaneseText>
      <EnglishText/>
      <Notes/>
      <Id>72</Id>
      <Status>To Do</Status>
    </Entry>
    <Entry>
      <PointerOffset>1309</PointerOffset>
      <JapaneseText>決められるのって……おかしいよ！</JapaneseText>
      <EnglishText/>
      <Notes/>
      <Id>73</Id>
      <Status>To Do</Status>
    </Entry>
    <Entry>
      <PointerOffset>1342</PointerOffset>
      <JapaneseText>そういえば……ジーニアスは</JapaneseText>
      <EnglishText/>
      <Notes/>
      <Id>74</Id>
      <Status>To Do</Status>
    </Entry>
    <Entry>
      <PointerOffset>1370</PointerOffset>
      <JapaneseText>ハーフエルフなんだよな？</JapaneseText>
      <EnglishText/>
      <Notes/>
      <Id>75</Id>
      <Status>To Do</Status>
    </Entry>
    <Entry>
      <PointerOffset>1395</PointerOffset>
      <JapaneseText>うん……ギルドのみんなは優しいけど</JapaneseText>
      <EnglishText/>
      <Notes/>
      <Id>76</Id>
      <Status>To Do</Status>
    </Entry>
    <Entry>
      <PointerOffset>1431</PointerOffset>
      <JapaneseText>まだ、世界にはボク達への偏見が</JapaneseText>
      <EnglishText/>
      <Notes/>
      <Id>77</Id>
      <Status>To Do</Status>
    </Entry>
    <Entry>
      <PointerOffset>1463</PointerOffset>
      <JapaneseText>根強く残ってる……</JapaneseText>
      <EnglishText/>
      <Notes/>
      <Id>78</Id>
      <Status>To Do</Status>
    </Entry>
    <Entry>
      <PointerOffset>1482</PointerOffset>
      <JapaneseText>差別意識……ってやつか。</JapaneseText>
      <EnglishText/>
      <Notes/>
      <Id>79</Id>
      <Status>To Do</Status>
    </Entry>
    <Entry>
      <PointerOffset>1508</PointerOffset>
      <JapaneseText>難しいよな……</JapaneseText>
      <EnglishText/>
      <Notes/>
      <Id>80</Id>
      <Status>To Do</Status>
    </Entry>
    <Entry>
      <PointerOffset>1523</PointerOffset>
      <JapaneseText>……うん。　だからボクはもう</JapaneseText>
      <EnglishText/>
      <Notes/>
      <Id>81</Id>
      <Status>To Do</Status>
    </Entry>
    <Entry>
      <PointerOffset>1553</PointerOffset>
      <JapaneseText>カイウスの事、リカンツって</JapaneseText>
      <EnglishText/>
      <Notes/>
      <Id>82</Id>
      <Status>To Do</Status>
    </Entry>
    <Entry>
      <PointerOffset>1581</PointerOffset>
      <JapaneseText>呼びたくないんだ……</JapaneseText>
      <EnglishText/>
      <Notes/>
      <Id>83</Id>
      <Status>To Do</Status>
    </Entry>
    <Entry>
      <PointerOffset>1602</PointerOffset>
      <JapaneseText>……何も知らなくて、ごめんね</JapaneseText>
      <EnglishText/>
      <Notes/>
      <Id>84</Id>
      <Status>To Do</Status>
    </Entry>
    <Entry>
      <PointerOffset>1631</PointerOffset>
      <JapaneseText>……ジーニアス……</JapaneseText>
      <EnglishText/>
      <Notes/>
      <Id>85</Id>
      <Status>To Do</Status>
    </Entry>
  </Entries>
</SceneText>