<?xml version="1.0" ?>
<Entries>
  <Entry>
    <PointerOffset>460</PointerOffset>
    <JapaneseText>そういえば、ルビアはどうして</JapaneseText>
    <EnglishText></EnglishText>
    <Notes/>
    <Id>37</Id>
    <Status>To Do</Status>
  </Entry>
  <Entry>
    <PointerOffset>490</PointerOffset>
    <JapaneseText>ギルドにやって来たんだ？</JapaneseText>
    <EnglishText></EnglishText>
    <Notes/>
    <Id>38</Id>
    <Status>To Do</Status>
  </Entry>
  <Entry>
    <PointerOffset>515</PointerOffset>
    <JapaneseText>確か、結成時の初期メンバーだと聞いたが</JapaneseText>
    <EnglishText></EnglishText>
    <Notes/>
    <Id>39</Id>
    <Status>To Do</Status>
  </Entry>
  <Entry>
    <PointerOffset>554</PointerOffset>
    <JapaneseText>そっか。</JapaneseText>
    <EnglishText></EnglishText>
    <Notes/>
    <Id>40</Id>
    <Status>To Do</Status>
  </Entry>
  <Entry>
    <PointerOffset>564</PointerOffset>
    <JapaneseText>ウィルさんにはまだ</JapaneseText>
    <EnglishText></EnglishText>
    <Notes/>
    <Id>41</Id>
    <Status>To Do</Status>
  </Entry>
  <Entry>
    <PointerOffset>584</PointerOffset>
    <JapaneseText>話した事なかったのよね</JapaneseText>
    <EnglishText></EnglishText>
    <Notes/>
    <Id>42</Id>
    <Status>To Do</Status>
  </Entry>
  <Entry>
    <PointerOffset>607</PointerOffset>
    <JapaneseText>……実は、故郷で色々あって</JapaneseText>
    <EnglishText></EnglishText>
    <Notes/>
    <Id>43</Id>
    <Status>To Do</Status>
  </Entry>
  <Entry>
    <PointerOffset>635</PointerOffset>
    <JapaneseText>何が正しくて何が正しくないのか</JapaneseText>
    <EnglishText></EnglishText>
    <Notes/>
    <Id>44</Id>
    <Status>To Do</Status>
  </Entry>
  <Entry>
    <PointerOffset>667</PointerOffset>
    <JapaneseText>ちょっとわからなくなっちゃったの</JapaneseText>
    <EnglishText></EnglishText>
    <Notes/>
    <Id>45</Id>
    <Status>To Do</Status>
  </Entry>
  <Entry>
    <PointerOffset>700</PointerOffset>
    <JapaneseText>でも、みんなが安心して暮らす為に</JapaneseText>
    <EnglishText></EnglishText>
    <Notes/>
    <Id>46</Id>
    <Status>To Do</Status>
  </Entry>
  <Entry>
    <PointerOffset>734</PointerOffset>
    <JapaneseText>ギルドを立ち上げてお手伝いをするっていう</JapaneseText>
    <EnglishText></EnglishText>
    <Notes/>
    <Id>47</Id>
    <Status>To Do</Status>
  </Entry>
  <Entry>
    <PointerOffset>776</PointerOffset>
    <JapaneseText>アンジュさんの考えは正しいと思ったわ</JapaneseText>
    <EnglishText></EnglishText>
    <Notes/>
    <Id>48</Id>
    <Status>To Do</Status>
  </Entry>
  <Entry>
    <PointerOffset>813</PointerOffset>
    <JapaneseText>だから、出来る事をしながら</JapaneseText>
    <EnglishText></EnglishText>
    <Notes/>
    <Id>49</Id>
    <Status>To Do</Status>
  </Entry>
  <Entry>
    <PointerOffset>841</PointerOffset>
    <JapaneseText>あたしはあたしで</JapaneseText>
    <EnglishText></EnglishText>
    <Notes/>
    <Id>50</Id>
    <Status>To Do</Status>
  </Entry>
  <Entry>
    <PointerOffset>859</PointerOffset>
    <JapaneseText>色々考えてみようと思ったの</JapaneseText>
    <EnglishText></EnglishText>
    <Notes/>
    <Id>51</Id>
    <Status>To Do</Status>
  </Entry>
  <Entry>
    <PointerOffset>886</PointerOffset>
    <JapaneseText>そうか。</JapaneseText>
    <EnglishText></EnglishText>
    <Notes/>
    <Id>52</Id>
    <Status>To Do</Status>
  </Entry>
  <Entry>
    <PointerOffset>896</PointerOffset>
    <JapaneseText>……答えは見つかりそうか？</JapaneseText>
    <EnglishText></EnglishText>
    <Notes/>
    <Id>53</Id>
    <Status>To Do</Status>
  </Entry>
  <Entry>
    <PointerOffset>923</PointerOffset>
    <JapaneseText>正直、まだまだ考え中</JapaneseText>
    <EnglishText></EnglishText>
    <Notes/>
    <Id>54</Id>
    <Status>To Do</Status>
  </Entry>
  <Entry>
    <PointerOffset>944</PointerOffset>
    <JapaneseText>でも、そんな簡単に答えがわかったら</JapaneseText>
    <EnglishText></EnglishText>
    <Notes/>
    <Id>55</Id>
    <Status>To Do</Status>
  </Entry>
  <Entry>
    <PointerOffset>980</PointerOffset>
    <JapaneseText>つまらないじゃない？</JapaneseText>
    <EnglishText></EnglishText>
    <Notes/>
    <Id>56</Id>
    <Status>To Do</Status>
  </Entry>
  <Entry>
    <PointerOffset>1001</PointerOffset>
    <JapaneseText>時間がかかってもいいの。</JapaneseText>
    <EnglishText></EnglishText>
    <Notes/>
    <Id>57</Id>
    <Status>To Do</Status>
  </Entry>
  <Entry>
    <PointerOffset>1027</PointerOffset>
    <JapaneseText>あたしは、本当の事が知りたい</JapaneseText>
    <EnglishText></EnglishText>
    <Notes/>
    <Id>58</Id>
    <Status>To Do</Status>
  </Entry>
  <Entry>
    <PointerOffset>1056</PointerOffset>
    <JapaneseText>焦ってウソの情報に踊らされるより</JapaneseText>
    <EnglishText></EnglishText>
    <Notes/>
    <Id>59</Id>
    <Status>To Do</Status>
  </Entry>
  <Entry>
    <PointerOffset>1090</PointerOffset>
    <JapaneseText>そっちの方がずっとマシよ</JapaneseText>
    <EnglishText></EnglishText>
    <Notes/>
    <Id>60</Id>
    <Status>To Do</Status>
  </Entry>
  <Entry>
    <PointerOffset>1115</PointerOffset>
    <JapaneseText>気が強いとは思っていたが</JapaneseText>
    <EnglishText></EnglishText>
    <Notes/>
    <Id>61</Id>
    <Status>To Do</Status>
  </Entry>
  <Entry>
    <PointerOffset>1141</PointerOffset>
    <JapaneseText>これは予想以上だな</JapaneseText>
    <EnglishText></EnglishText>
    <Notes/>
    <Id>62</Id>
    <Status>To Do</Status>
  </Entry>
  <Entry>
    <PointerOffset>1160</PointerOffset>
    <JapaneseText>しっかりしたお嬢さんだ</JapaneseText>
    <EnglishText></EnglishText>
    <Notes/>
    <Id>63</Id>
    <Status>To Do</Status>
  </Entry>
  <Entry>
    <PointerOffset>1183</PointerOffset>
    <JapaneseText>うふふ、当然よ</JapaneseText>
    <EnglishText></EnglishText>
    <Notes/>
    <Id>64</Id>
    <Status>To Do</Status>
  </Entry>
  <Entry>
    <PointerOffset>1198</PointerOffset>
    <JapaneseText>あたしはカイウスのお守りも</JapaneseText>
    <EnglishText></EnglishText>
    <Notes/>
    <Id>65</Id>
    <Status>To Do</Status>
  </Entry>
  <Entry>
    <PointerOffset>1226</PointerOffset>
    <JapaneseText>してるんですからね♪</JapaneseText>
    <EnglishText></EnglishText>
    <Notes/>
    <Id>66</Id>
    <Status>To Do</Status>
  </Entry>
</Entries>
