<?xml version='1.0' encoding='utf-8'?>
<Entries>
  <Entry>
    <PointerOffsetDec>789</PointerOffsetDec>
    <PointerOffsetHex>0x315</PointerOffsetHex>
    <JapaneseText>お招きどうもありがとさん</JapaneseText>
    <EnglishText></EnglishText>
    <Notes />
    <Id>51</Id>
    <Status />
  </Entry>
  <Entry>
    <PointerOffsetDec>814</PointerOffsetDec>
    <PointerOffsetHex>0x32e</PointerOffsetHex>
    <JapaneseText>気持ちは変わらないのか</JapaneseText>
    <EnglishText></EnglishText>
    <Notes />
    <Id>52</Id>
    <Status />
  </Entry>
  <Entry>
    <PointerOffsetDec>837</PointerOffsetDec>
    <PointerOffsetHex>0x345</PointerOffsetHex>
    <JapaneseText>何度も言わせんなって</JapaneseText>
    <EnglishText></EnglishText>
    <Notes />
    <Id>53</Id>
    <Status />
  </Entry>
  <Entry>
    <PointerOffsetDec>858</PointerOffsetDec>
    <PointerOffsetHex>0x35a</PointerOffsetHex>
    <JapaneseText>お前には、お前の。</JapaneseText>
    <EnglishText></EnglishText>
    <Notes />
    <Id>54</Id>
    <Status />
  </Entry>
  <Entry>
    <PointerOffsetDec>878</PointerOffsetDec>
    <PointerOffsetHex>0x36e</PointerOffsetHex>
    <JapaneseText>オレには、オレのやり方がある。</JapaneseText>
    <EnglishText></EnglishText>
    <Notes />
    <Id>55</Id>
    <Status />
  </Entry>
  <Entry>
    <PointerOffsetDec>910</PointerOffsetDec>
    <PointerOffsetHex>0x38e</PointerOffsetHex>
    <JapaneseText>そんだけの話だろ</JapaneseText>
    <EnglishText></EnglishText>
    <Notes />
    <Id>56</Id>
    <Status />
  </Entry>
  <Entry>
    <PointerOffsetDec>927</PointerOffsetDec>
    <PointerOffsetHex>0x39f</PointerOffsetHex>
    <JapaneseText>万人が等しく扱われる法秩序を築く……。</JapaneseText>
    <EnglishText></EnglishText>
    <Notes />
    <Id>57</Id>
    <Status />
  </Entry>
  <Entry>
    <PointerOffsetDec>967</PointerOffsetDec>
    <PointerOffsetHex>0x3c7</PointerOffsetHex>
    <JapaneseText>それが僕の願いであり、目的だ</JapaneseText>
    <EnglishText></EnglishText>
    <Notes />
    <Id>58</Id>
    <Status />
  </Entry>
  <Entry>
    <PointerOffsetDec>996</PointerOffsetDec>
    <PointerOffsetHex>0x3e4</PointerOffsetHex>
    <JapaneseText>だけどユーリ、君だって思いは同じはず。</JapaneseText>
    <EnglishText></EnglishText>
    <Notes />
    <Id>59</Id>
    <Status />
  </Entry>
  <Entry>
    <PointerOffsetDec>1036</PointerOffsetDec>
    <PointerOffsetHex>0x40c</PointerOffsetHex>
    <JapaneseText>だからこそ、一度は騎士団の門を</JapaneseText>
    <EnglishText></EnglishText>
    <Notes />
    <Id>60</Id>
    <Status />
  </Entry>
  <Entry>
    <PointerOffsetDec>1068</PointerOffsetDec>
    <PointerOffsetHex>0x42c</PointerOffsetHex>
    <JapaneseText>叩いたんだろう？</JapaneseText>
    <EnglishText></EnglishText>
    <Notes />
    <Id>61</Id>
    <Status />
  </Entry>
  <Entry>
    <PointerOffsetDec>1085</PointerOffsetDec>
    <PointerOffsetHex>0x43d</PointerOffsetHex>
    <JapaneseText>じゃあ、お前、騎士団に入って</JapaneseText>
    <EnglishText></EnglishText>
    <Notes />
    <Id>62</Id>
    <Status />
  </Entry>
  <Entry>
    <PointerOffsetDec>1115</PointerOffsetDec>
    <PointerOffsetHex>0x45b</PointerOffsetHex>
    <JapaneseText>何か変わったのか？</JapaneseText>
    <EnglishText></EnglishText>
    <Notes />
    <Id>63</Id>
    <Status />
  </Entry>
  <Entry>
    <PointerOffsetDec>1135</PointerOffsetDec>
    <PointerOffsetHex>0x46f</PointerOffsetHex>
    <JapaneseText>変えられたのかよ？</JapaneseText>
    <EnglishText></EnglishText>
    <Notes />
    <Id>64</Id>
    <Status />
  </Entry>
  <Entry>
    <PointerOffsetDec>1154</PointerOffsetDec>
    <PointerOffsetHex>0x482</PointerOffsetHex>
    <JapaneseText>確かに、まだやりきれていない事はある。</JapaneseText>
    <EnglishText></EnglishText>
    <Notes />
    <Id>65</Id>
    <Status />
  </Entry>
  <Entry>
    <PointerOffsetDec>1194</PointerOffsetDec>
    <PointerOffsetHex>0x4aa</PointerOffsetHex>
    <JapaneseText>だからと言って君の様に、</JapaneseText>
    <EnglishText></EnglishText>
    <Notes />
    <Id>66</Id>
    <Status />
  </Entry>
  <Entry>
    <PointerOffsetDec>1220</PointerOffsetDec>
    <PointerOffsetHex>0x4c4</PointerOffsetHex>
    <JapaneseText>人が人を裁く道を肯定する事は出来ない</JapaneseText>
    <EnglishText></EnglishText>
    <Notes />
    <Id>67</Id>
    <Status />
  </Entry>
  <Entry>
    <PointerOffsetDec>1257</PointerOffsetDec>
    <PointerOffsetHex>0x4e9</PointerOffsetHex>
    <JapaneseText>認めるわけにはいかないんだ……</JapaneseText>
    <EnglishText></EnglishText>
    <Notes />
    <Id>68</Id>
    <Status />
  </Entry>
  <Entry>
    <PointerOffsetDec>1288</PointerOffsetDec>
    <PointerOffsetHex>0x508</PointerOffsetHex>
    <JapaneseText>……もう一度聞く。</JapaneseText>
    <EnglishText></EnglishText>
    <Notes />
    <Id>69</Id>
    <Status />
  </Entry>
  <Entry>
    <PointerOffsetDec>1308</PointerOffsetDec>
    <PointerOffsetHex>0x51c</PointerOffsetHex>
    <JapaneseText>それでも、気持ちは変わらないか？</JapaneseText>
    <EnglishText></EnglishText>
    <Notes />
    <Id>70</Id>
    <Status />
  </Entry>
  <Entry>
    <PointerOffsetDec>1341</PointerOffsetDec>
    <PointerOffsetHex>0x53d</PointerOffsetHex>
    <JapaneseText>いい加減、この問答にも飽きてきたな</JapaneseText>
    <EnglishText></EnglishText>
    <Notes />
    <Id>71</Id>
    <Status />
  </Entry>
  <Entry>
    <PointerOffsetDec>1376</PointerOffsetDec>
    <PointerOffsetHex>0x560</PointerOffsetHex>
    <JapaneseText>そうか……ならば</JapaneseText>
    <EnglishText></EnglishText>
    <Notes />
    <Id>72</Id>
    <Status />
  </Entry>
  <Entry>
    <PointerOffsetDec>1393</PointerOffsetDec>
    <PointerOffsetHex>0x571</PointerOffsetHex>
    <JapaneseText>こうするより他に</JapaneseText>
    <EnglishText></EnglishText>
    <Notes />
    <Id>73</Id>
    <Status />
  </Entry>
  <Entry>
    <PointerOffsetDec>1411</PointerOffsetDec>
    <PointerOffsetHex>0x583</PointerOffsetHex>
    <JapaneseText>道はないという事だな</JapaneseText>
    <EnglishText></EnglishText>
    <Notes />
    <Id>74</Id>
    <Status />
  </Entry>
  <Entry>
    <PointerOffsetDec>1432</PointerOffsetDec>
    <PointerOffsetHex>0x598</PointerOffsetHex>
    <JapaneseText>そういうこったな</JapaneseText>
    <EnglishText></EnglishText>
    <Notes />
    <Id>75</Id>
    <Status />
  </Entry>
  <Entry>
    <PointerOffsetDec>1449</PointerOffsetDec>
    <PointerOffsetHex>0x5a9</PointerOffsetHex>
    <JapaneseText>んじゃ、行くぜ！</JapaneseText>
    <EnglishText></EnglishText>
    <Notes />
    <Id>76</Id>
    <Status />
  </Entry>
</Entries>