<SceneText>
  <FriendlyName></FriendlyName>
  <Speakers/>
    <Section></Section>
  <Entries>
    <Entry>
      <PointerOffset>324</PointerOffset>
      <JapaneseText>そうそう「料理」について</JapaneseText>
      <EnglishText/>
      <Notes/>
      <Id>25</Id>
      <Status>To Do</Status>
    </Entry>
    <Entry>
      <PointerOffset>350</PointerOffset>
      <JapaneseText>お教えしますね</JapaneseText>
      <EnglishText/>
      <Notes/>
      <Id>26</Id>
      <Status>To Do</Status>
    </Entry>
    <Entry>
      <PointerOffset>365</PointerOffset>
      <JapaneseText>料理はレシピを入手し、かつ料理に必要な</JapaneseText>
      <EnglishText/>
      <Notes/>
      <Id>27</Id>
      <Status>To Do</Status>
    </Entry>
    <Entry>
      <PointerOffset>405</PointerOffset>
      <JapaneseText>食材があれば、「生産」によって作る事が</JapaneseText>
      <EnglishText/>
      <Notes/>
      <Id>28</Id>
      <Status>To Do</Status>
    </Entry>
    <Entry>
      <PointerOffset>445</PointerOffset>
      <JapaneseText>出来ます</JapaneseText>
      <EnglishText/>
      <Notes/>
      <Id>29</Id>
      <Status>To Do</Status>
    </Entry>
    <Entry>
      <PointerOffset>454</PointerOffset>
      <JapaneseText>ただ、料理を作る事が出来るのは、</JapaneseText>
      <EnglishText/>
      <Notes/>
      <Id>30</Id>
      <Status>To Do</Status>
    </Entry>
    <Entry>
      <PointerOffset>488</PointerOffset>
      <JapaneseText>ダンジョンの中、しかもメニューを</JapaneseText>
      <EnglishText/>
      <Notes/>
      <Id>31</Id>
      <Status>To Do</Status>
    </Entry>
    <Entry>
      <PointerOffset>522</PointerOffset>
      <JapaneseText>開く事が出来るタイミングだけです</JapaneseText>
      <EnglishText/>
      <Notes/>
      <Id>32</Id>
      <Status>To Do</Status>
    </Entry>
    <Entry>
      <PointerOffset>555</PointerOffset>
      <JapaneseText>こうして出来た料理を食べる事によって、</JapaneseText>
      <EnglishText/>
      <Notes/>
      <Id>33</Id>
      <Status>To Do</Status>
    </Entry>
    <Entry>
      <PointerOffset>595</PointerOffset>
      <JapaneseText>パーティ全員には様々な効果をもたらします</JapaneseText>
      <EnglishText/>
      <Notes/>
      <Id>34</Id>
      <Status>To Do</Status>
    </Entry>
    <Entry>
      <PointerOffset>636</PointerOffset>
      <JapaneseText>例えば最大ＨＰやＴＰの増加、</JapaneseText>
      <EnglishText/>
      <Notes/>
      <Id>35</Id>
      <Status>To Do</Status>
    </Entry>
    <Entry>
      <PointerOffset>666</PointerOffset>
      <JapaneseText>パラメータの上昇など、様々な効果があります</JapaneseText>
      <EnglishText/>
      <Notes/>
      <Id>36</Id>
      <Status>To Do</Status>
    </Entry>
    <Entry>
      <PointerOffset>709</PointerOffset>
      <JapaneseText>この効果は、ダンジョンにいる間継続します。</JapaneseText>
      <EnglishText/>
      <Notes/>
      <Id>37</Id>
      <Status>To Do</Status>
    </Entry>
    <Entry>
      <PointerOffset>753</PointerOffset>
      <JapaneseText>ただし…、</JapaneseText>
      <EnglishText/>
      <Notes/>
      <Id>38</Id>
      <Status>To Do</Status>
    </Entry>
    <Entry>
      <PointerOffset>764</PointerOffset>
      <JapaneseText>ダンジョンから出たり、パーティが全滅して</JapaneseText>
      <EnglishText/>
      <Notes/>
      <Id>39</Id>
      <Status>To Do</Status>
    </Entry>
    <Entry>
      <PointerOffset>806</PointerOffset>
      <JapaneseText>しまった場合は解除されます</JapaneseText>
      <EnglishText/>
      <Notes/>
      <Id>40</Id>
      <Status>To Do</Status>
    </Entry>
    <Entry>
      <PointerOffset>833</PointerOffset>
      <JapaneseText>ちなみに効果継続中に、また新しい料理を</JapaneseText>
      <EnglishText/>
      <Notes/>
      <Id>41</Id>
      <Status>To Do</Status>
    </Entry>
    <Entry>
      <PointerOffset>873</PointerOffset>
      <JapaneseText>作って食べた場合、今までの効果は無効と</JapaneseText>
      <EnglishText/>
      <Notes/>
      <Id>42</Id>
      <Status>To Do</Status>
    </Entry>
    <Entry>
      <PointerOffset>913</PointerOffset>
      <JapaneseText>なります</JapaneseText>
      <EnglishText/>
      <Notes/>
      <Id>43</Id>
      <Status>To Do</Status>
    </Entry>
    <Entry>
      <PointerOffset>922</PointerOffset>
      <JapaneseText>その代わり、新たに食べた料理の効果を</JapaneseText>
      <EnglishText/>
      <Notes/>
      <Id>44</Id>
      <Status>To Do</Status>
    </Entry>
    <Entry>
      <PointerOffset>960</PointerOffset>
      <JapaneseText>得られる、という事です</JapaneseText>
      <EnglishText/>
      <Notes/>
      <Id>45</Id>
      <Status>To Do</Status>
    </Entry>
    <Entry>
      <PointerOffset>983</PointerOffset>
      <JapaneseText>ですので、ダンジョン内の状況によって</JapaneseText>
      <EnglishText/>
      <Notes/>
      <Id>46</Id>
      <Status>To Do</Status>
    </Entry>
    <Entry>
      <PointerOffset>1021</PointerOffset>
      <JapaneseText>作る料理の献立を決めるといいと思いますよ</JapaneseText>
      <EnglishText/>
      <Notes/>
      <Id>47</Id>
      <Status>To Do</Status>
    </Entry>
    <Entry>
      <PointerOffset>1062</PointerOffset>
      <JapaneseText>以上、せん越ながら</JapaneseText>
      <EnglishText/>
      <Notes/>
      <Id>48</Id>
      <Status>To Do</Status>
    </Entry>
    <Entry>
      <PointerOffset>1082</PointerOffset>
      <JapaneseText>説明させていただきました</JapaneseText>
      <EnglishText/>
      <Notes/>
      <Id>49</Id>
      <Status>To Do</Status>
    </Entry>
  </Entries>
</SceneText>